textra.py
textra-0.6.dist-info/LICENSE
textra-0.6.dist-info/METADATA
textra-0.6.dist-info/WHEEL
textra-0.6.dist-info/entry_points.txt
textra-0.6.dist-info/top_level.txt
textra-0.6.dist-info/RECORD
