Metadata-Version: 2.1
Name: textra
Version: 0.6
Summary: Machine translation for Everyone
Home-page: https://github.com/GitHub30/textra
Author: TexTra
Author-email: funaox@gmail.com
License: MIT
Project-URL: Bug Tracker, https://github.com/GitHub30/textra/issues
Keywords: TexTra translation python
Platform: any
Classifier: Operating System :: OS Independent
Classifier: Programming Language :: Python :: 3
Classifier: License :: OSI Approved :: MIT License
Classifier: Topic :: Utilities
Classifier: Topic :: Software Development :: Libraries :: Python Modules
License-File: LICENSE
Requires-Dist: requests
Requires-Dist: requests-oauthlib
